jb3/__init__.py
jb3/analytics/montecarlo.py
jb3/data/__init__.py
jb3/data/fred.py
jb3/data/ljse.py
jb3/data/nasdaq.py
jb3/plot/plot.py
jb3-0.1.4.dist-info/licenses/LICENSE
jb3-0.1.4.dist-info/METADATA
jb3-0.1.4.dist-info/WHEEL
jb3-0.1.4.dist-info/top_level.txt
jb3-0.1.4.dist-info/RECORD
