Metadata-Version: 2.4
Name: jb3
Version: 0.1.4
Summary: JB3 package – unified access to LJSE, FRED and NASDAQ financial data
Author-email: Janez Bucar <gospod.bucarrr@gmail.com>
License: MIT
Keywords: finance,stocks,nasdaq,ljse,fred,macro,economics,time-series,data
Classifier: Programming Language :: Python :: 3
Classifier: Programming Language :: Python :: 3 :: Only
Classifier: License :: OSI Approved :: MIT License
Classifier: Operating System :: OS Independent
Classifier: Intended Audience :: Financial and Insurance Industry
Classifier: Intended Audience :: Science/Research
Classifier: Topic :: Office/Business :: Financial :: Investment
Classifier: Topic :: Scientific/Engineering :: Information Analysis
Requires-Python: >=3.8
License-File: LICENSE
Requires-Dist: pandas
Requires-Dist: numpy
Requires-Dist: matplotlib
Requires-Dist: seaborn
Requires-Dist: requests
Requires-Dist: tqdm
Requires-Dist: ljse
Dynamic: license-file
